<?xml version="1.0" encoding="UTF-8" standalone="yes"?>
<bpmn:definitions xmlns:xsi="http://www.w3.org/2001/XMLSchema-instance" xmlns:bpmn="http://www.omg.org/spec/BPMN/20100524/MODEL" xmlns:camunda="http://camunda.org/schema/1.0/bpmn" xmlns:xs="http://www.w3.org/2001/XMLSchema" xmlns:bpmndi="http://www.omg.org/spec/BPMN/20100524/DI" xmlns:di="http://www.omg.org/spec/DD/20100524/DI" xmlns:ecos="http://www.citeck.ru/ecos/bpmn/1.0" xmlns:dc="http://www.omg.org/spec/DD/20100524/DC" id="Definitions_MqmbCzx" name="Процесс заявки на изменение" targetNamespace="http://bpmn.io/schema/bpmn" exporter="bpmn-js (https://demo.bpmn.io)" exporterVersion="8.2.0" ecos:workingCopySourceRef="" ecos:name_ml="{&quot;ru&quot;:&quot;Процесс заявки на изменение&quot;,&quot;en&quot;:&quot;Change request process&quot;}" ecos:formRef="" ecos:sectionRef="eproc/bpmn-section@DEFAULT" ecos:enabled="true" ecos:autoStartEnabled="true" ecos:defState="CONVERTED" ecos:processDefId="change-request-process" ecos:ecosType="emodel/type@cr-type">
    <bpmn:process isExecutable="true" id="change-request-process">
        <bpmn:startEvent isInterrupting="true" name="" id="StartEvent_1ew9rff" ecos:documentation="{}" ecos:asyncConfig="{&quot;asyncBefore&quot;:false,&quot;asyncAfter&quot;:false,&quot;exclusive&quot;:true}" ecos:name_ml="{}" ecos:jobConfig="{&quot;jobPriority&quot;:null,&quot;jobRetryTimeCycle&quot;:null}">
            <bpmn:outgoing >Flow_18gcg86</bpmn:outgoing>
        </bpmn:startEvent>
        <bpmn:endEvent name="" id="Event_1xysdvv" ecos:documentation="{}" ecos:asyncConfig="{&quot;asyncBefore&quot;:false,&quot;asyncAfter&quot;:false,&quot;exclusive&quot;:true}" ecos:name_ml="{}" ecos:jobConfig="{&quot;jobPriority&quot;:null,&quot;jobRetryTimeCycle&quot;:null}">
            <bpmn:incoming >Flow_1rhkg15</bpmn:incoming>
        </bpmn:endEvent>
        <bpmn:subProcess triggeredByEvent="false" name="" id="Activity_1orn22c" ecos:documentation="{}" ecos:asyncConfig="{&quot;asyncBefore&quot;:false,&quot;asyncAfter&quot;:false,&quot;exclusive&quot;:true}" ecos:name_ml="{}" ecos:jobConfig="{&quot;jobPriority&quot;:null,&quot;jobRetryTimeCycle&quot;:null}">
            <bpmn:incoming >Flow_1wl760w</bpmn:incoming>
            <bpmn:startEvent isInterrupting="true" name="" id="Event_0ye7f0f" ecos:documentation="{}" ecos:asyncConfig="{&quot;asyncBefore&quot;:false,&quot;asyncAfter&quot;:false,&quot;exclusive&quot;:true}" ecos:name_ml="{}" ecos:jobConfig="{&quot;jobPriority&quot;:null,&quot;jobRetryTimeCycle&quot;:null}">
                <bpmn:outgoing >Flow_0dmwh1t</bpmn:outgoing>
            </bpmn:startEvent>
            <bpmn:task name="" id="Activity_1vnq7vx" ecos:documentation="{}" ecos:asyncConfig="{&quot;asyncBefore&quot;:false,&quot;asyncAfter&quot;:false,&quot;exclusive&quot;:true}" ecos:taskType="setStatus" ecos:name_ml="{}" ecos:jobConfig="{&quot;jobPriority&quot;:null,&quot;jobRetryTimeCycle&quot;:null}" ecos:status="cr-approving">
                <bpmn:incoming >Flow_0dmwh1t</bpmn:incoming>
                <bpmn:outgoing >Flow_1rgsdw4</bpmn:outgoing>
            </bpmn:task>
            <bpmn:sequenceFlow sourceRef="Event_0ye7f0f" targetRef="Activity_1vnq7vx" name="" id="Flow_0dmwh1t" ecos:name_ml="{}" ecos:conditionConfig="{&quot;fn&quot;:&quot; &quot;,&quot;expression&quot;:&quot;&quot;,&quot;outcome&quot;:&quot;&quot;}" ecos:conditionType="NONE"/>
            <bpmn:endEvent name="" id="Event_18geua4" ecos:documentation="{}" ecos:asyncConfig="{&quot;asyncBefore&quot;:false,&quot;asyncAfter&quot;:false,&quot;exclusive&quot;:true}" ecos:errorName="cr-checking" ecos:name_ml="{}" ecos:jobConfig="{&quot;jobPriority&quot;:null,&quot;jobRetryTimeCycle&quot;:null}" ecos:errorCode="cr-checking">
                <bpmn:incoming >Flow_0wlz4dd</bpmn:incoming>
                <bpmn:errorEventDefinition  errorRef="Error_3Sl7lFV" id="ErrorEventDefinition_0rhft30"/>
            </bpmn:endEvent>
            <bpmn:sequenceFlow sourceRef="Activity_1vnq7vx" targetRef="Activity_0hgdfsc" name="" id="Flow_1rgsdw4" ecos:name_ml="{}" ecos:conditionConfig="{&quot;fn&quot;:&quot; &quot;,&quot;expression&quot;:&quot;&quot;,&quot;outcome&quot;:&quot;&quot;}" ecos:conditionType="NONE"/>
            <bpmn:sequenceFlow sourceRef="Activity_0hgdfsc" targetRef="Gateway_1uec1ao" name="" id="Flow_0hubowj" ecos:name_ml="{}" ecos:conditionConfig="{&quot;fn&quot;:&quot;&quot;,&quot;expression&quot;:&quot;&quot;,&quot;outcome&quot;:&quot;&quot;}" ecos:conditionType="NONE"/>
            <bpmn:userTask name="Согласование" id="Activity_0hgdfsc" ecos:documentation="{}" ecos:manualRecipients="[]" ecos:outcomes="[{&quot;id&quot;:&quot;approved&quot;,&quot;name&quot;:{&quot;ru&quot;:&quot;Согласовано&quot;},&quot;config&quot;:{&quot;theme&quot;:&quot;PRIMARY&quot;}},{&quot;id&quot;:&quot;rework&quot;,&quot;name&quot;:{&quot;ru&quot;:&quot;На доработку&quot;},&quot;config&quot;:{&quot;theme&quot;:&quot;PRIMARY&quot;}}]" ecos:laEnabled="false" ecos:name_ml="{&quot;ru&quot;:&quot;Согласование&quot;}" ecos:laNotificationType="EMAIL_NOTIFICATION" ecos:manualRecipientsMode="false" ecos:priority="MEDIUM" ecos:multiInstanceConfig="{&quot;sequential&quot;:false,&quot;collection&quot;:&quot;&quot;,&quot;element&quot;:&quot;&quot;,&quot;loopCardinality&quot;:&quot;&quot;,&quot;completionCondition&quot;:&quot;&quot;,&quot;asyncConfig&quot;:{&quot;asyncBefore&quot;:false,&quot;asyncAfter&quot;:false,&quot;exclusive&quot;:true},&quot;jobConfig&quot;:{&quot;jobPriority&quot;:null,&quot;jobRetryTimeCycle&quot;:&quot;&quot;}}" ecos:assignees="[&quot;initiator-role&quot;,&quot;initiator-leader-role&quot;,&quot;department-leader-role&quot;,&quot;additional-approvers-role&quot;]">
                <bpmn:incoming >Flow_1rgsdw4</bpmn:incoming>
                <bpmn:outgoing >Flow_0hubowj</bpmn:outgoing>
                <bpmn:multiInstanceLoopCharacteristics isSequential="false" camunda:asyncBefore="false" camunda:exclusive="true" camunda:asyncAfter="false">
                    <bpmn:extensionElements/>
                </bpmn:multiInstanceLoopCharacteristics>
            </bpmn:userTask>
            <bpmn:exclusiveGateway name="" id="Gateway_1uec1ao" ecos:documentation="{}" ecos:name_ml="{}">
                <bpmn:incoming >Flow_0hubowj</bpmn:incoming>
                <bpmn:outgoing >Flow_0wlz4dd</bpmn:outgoing>
                <bpmn:outgoing >Flow_004vsfw</bpmn:outgoing>
            </bpmn:exclusiveGateway>
            <bpmn:sequenceFlow sourceRef="Gateway_1uec1ao" targetRef="Event_18geua4" name="" id="Flow_0wlz4dd" ecos:name_ml="{}" ecos:conditionConfig="{&quot;fn&quot;:&quot;&quot;,&quot;expression&quot;:&quot;&quot;,&quot;outcome&quot;:&quot;Activity_0hgdfsc:approved&quot;}" ecos:conditionType="OUTCOME"/>
            <bpmn:endEvent name="" id="Event_1c358pb" ecos:documentation="{}" ecos:asyncConfig="{&quot;asyncBefore&quot;:false,&quot;asyncAfter&quot;:false,&quot;exclusive&quot;:true}" ecos:errorName="cr-rework" ecos:name_ml="{}" ecos:jobConfig="{&quot;jobPriority&quot;:null,&quot;jobRetryTimeCycle&quot;:null}" ecos:errorCode="cr-rework">
                <bpmn:incoming >Flow_004vsfw</bpmn:incoming>
                <bpmn:errorEventDefinition  errorRef="Error_ODErKks" id="ErrorEventDefinition_0qf0c28"/>
            </bpmn:endEvent>
            <bpmn:sequenceFlow sourceRef="Gateway_1uec1ao" targetRef="Event_1c358pb" name="" id="Flow_004vsfw" ecos:name_ml="{}" ecos:conditionConfig="{&quot;fn&quot;:&quot;&quot;,&quot;expression&quot;:&quot;&quot;,&quot;outcome&quot;:&quot;Activity_0hgdfsc:rework&quot;}" ecos:conditionType="OUTCOME"/>
        </bpmn:subProcess>
        <bpmn:boundaryEvent  cancelActivity="true" attachedToRef="Activity_1orn22c" name="" id="Event_00uj5gg" ecos:documentation="{}" ecos:asyncConfig="{&quot;asyncBefore&quot;:false,&quot;asyncAfter&quot;:false,&quot;exclusive&quot;:true}" ecos:errorName="catch-cr-checking" ecos:name_ml="{}" ecos:jobConfig="{&quot;jobPriority&quot;:null,&quot;jobRetryTimeCycle&quot;:null}" ecos:errorCode="cr-checking">
            <bpmn:outgoing>Flow_1104ytg</bpmn:outgoing>
            <bpmn:errorEventDefinition errorRef="Error_Fuw42ho" id="ErrorEventDefinition_1qpzq4w"/>
        </bpmn:boundaryEvent>
        <bpmn:subProcess triggeredByEvent="false" name="" id="Activity_0u2ji26" ecos:documentation="{}" ecos:asyncConfig="{&quot;asyncBefore&quot;:false,&quot;asyncAfter&quot;:false,&quot;exclusive&quot;:true}" ecos:name_ml="{}" ecos:jobConfig="{&quot;jobPriority&quot;:null,&quot;jobRetryTimeCycle&quot;:null}">
            <bpmn:incoming >Flow_1104ytg</bpmn:incoming>
            <bpmn:startEvent isInterrupting="true" name="" id="Event_1ycb2rd" ecos:documentation="{}" ecos:asyncConfig="{&quot;asyncBefore&quot;:false,&quot;asyncAfter&quot;:false,&quot;exclusive&quot;:true}" ecos:name_ml="{}" ecos:jobConfig="{&quot;jobPriority&quot;:null,&quot;jobRetryTimeCycle&quot;:null}">
                <bpmn:outgoing >Flow_0rsmpbt</bpmn:outgoing>
            </bpmn:startEvent>
            <bpmn:task name="" id="Activity_06yomsp" ecos:documentation="{}" ecos:asyncConfig="{&quot;asyncBefore&quot;:false,&quot;asyncAfter&quot;:false,&quot;exclusive&quot;:true}" ecos:taskType="setStatus" ecos:name_ml="{}" ecos:jobConfig="{&quot;jobPriority&quot;:null,&quot;jobRetryTimeCycle&quot;:null}" ecos:status="cr-checking">
                <bpmn:incoming >Flow_0rsmpbt</bpmn:incoming>
                <bpmn:outgoing >Flow_1e5og53</bpmn:outgoing>
            </bpmn:task>
            <bpmn:endEvent name="" id="Event_1lvltfg" ecos:documentation="{}" ecos:asyncConfig="{&quot;asyncBefore&quot;:false,&quot;asyncAfter&quot;:false,&quot;exclusive&quot;:true}" ecos:errorName="cr-registration" ecos:name_ml="{}" ecos:jobConfig="{&quot;jobPriority&quot;:null,&quot;jobRetryTimeCycle&quot;:null}" ecos:errorCode="cr-registration">
                <bpmn:incoming >Flow_09l4mlz</bpmn:incoming>
                <bpmn:errorEventDefinition  errorRef="Error_opWhdMs" id="ErrorEventDefinition_0pnsh8c"/>
            </bpmn:endEvent>
            <bpmn:sequenceFlow sourceRef="Event_1ycb2rd" targetRef="Activity_06yomsp" name="" id="Flow_0rsmpbt" ecos:name_ml="{}" ecos:conditionConfig="{&quot;fn&quot;:&quot; &quot;,&quot;expression&quot;:&quot;&quot;,&quot;outcome&quot;:&quot;&quot;}" ecos:conditionType="NONE"/>
            <bpmn:sequenceFlow sourceRef="Activity_06yomsp" targetRef="Activity_0f2qbi5" name="" id="Flow_1e5og53" ecos:name_ml="{}" ecos:conditionConfig="{&quot;fn&quot;:&quot; &quot;,&quot;expression&quot;:&quot;&quot;,&quot;outcome&quot;:&quot;&quot;}" ecos:conditionType="NONE"/>
            <bpmn:sequenceFlow sourceRef="Activity_0f2qbi5" targetRef="Event_1lvltfg" name="" id="Flow_09l4mlz" ecos:name_ml="{}" ecos:conditionConfig="{&quot;fn&quot;:&quot;&quot;,&quot;expression&quot;:&quot;&quot;,&quot;outcome&quot;:&quot;&quot;}" ecos:conditionType="NONE"/>
            <bpmn:userTask name="Проверка" id="Activity_0f2qbi5" ecos:documentation="{}" ecos:manualRecipients="[]" ecos:outcomes="[{&quot;id&quot;:&quot;checked&quot;,&quot;name&quot;:{&quot;ru&quot;:&quot;Проверено&quot;,&quot;en&quot;:&quot;Checked&quot;},&quot;config&quot;:{&quot;theme&quot;:&quot;PRIMARY&quot;}}]" ecos:laEnabled="false" ecos:name_ml="{&quot;ru&quot;:&quot;Проверка&quot;}" ecos:laNotificationType="EMAIL_NOTIFICATION" ecos:manualRecipientsMode="false" ecos:priority="MEDIUM" ecos:assignees="[&quot;inspector-role&quot;]">
                <bpmn:incoming >Flow_1e5og53</bpmn:incoming>
                <bpmn:outgoing >Flow_09l4mlz</bpmn:outgoing>
            </bpmn:userTask>
        </bpmn:subProcess>
        <bpmn:sequenceFlow sourceRef="Event_00uj5gg" targetRef="Activity_0u2ji26" name="" id="Flow_1104ytg" ecos:name_ml="{}" ecos:conditionConfig="{&quot;fn&quot;:&quot; &quot;,&quot;expression&quot;:&quot;&quot;,&quot;outcome&quot;:&quot;&quot;}" ecos:conditionType="NONE"/>
        <bpmn:boundaryEvent  cancelActivity="true" attachedToRef="Activity_0u2ji26" name="" id="Event_06mr4j6" ecos:documentation="{}" ecos:asyncConfig="{&quot;asyncBefore&quot;:false,&quot;asyncAfter&quot;:false,&quot;exclusive&quot;:true}" ecos:errorName="catch-cr-registration" ecos:name_ml="{}" ecos:jobConfig="{&quot;jobPriority&quot;:null,&quot;jobRetryTimeCycle&quot;:null}" ecos:errorCode="cr-registration">
            <bpmn:outgoing>Flow_02c54hj</bpmn:outgoing>
            <bpmn:errorEventDefinition errorRef="Error_sB2Nnjm" id="ErrorEventDefinition_1qmijh8"/>
        </bpmn:boundaryEvent>
        <bpmn:subProcess triggeredByEvent="false" name="" id="Activity_06i9ief" ecos:documentation="{}" ecos:asyncConfig="{&quot;asyncBefore&quot;:false,&quot;asyncAfter&quot;:false,&quot;exclusive&quot;:true}" ecos:name_ml="{}" ecos:jobConfig="{&quot;jobPriority&quot;:null,&quot;jobRetryTimeCycle&quot;:null}">
            <bpmn:incoming >Flow_02c54hj</bpmn:incoming>
            <bpmn:startEvent isInterrupting="true" name="" id="Event_08y1fx0" ecos:documentation="{}" ecos:asyncConfig="{&quot;asyncBefore&quot;:false,&quot;asyncAfter&quot;:false,&quot;exclusive&quot;:true}" ecos:name_ml="{}" ecos:jobConfig="{&quot;jobPriority&quot;:null,&quot;jobRetryTimeCycle&quot;:null}">
                <bpmn:outgoing >Flow_1j4kz66</bpmn:outgoing>
            </bpmn:startEvent>
            <bpmn:endEvent name="" id="Event_0nnj983" ecos:documentation="{}" ecos:asyncConfig="{&quot;asyncBefore&quot;:false,&quot;asyncAfter&quot;:false,&quot;exclusive&quot;:true}" ecos:errorName="cr-action-plan-creating" ecos:name_ml="{}" ecos:jobConfig="{&quot;jobPriority&quot;:null,&quot;jobRetryTimeCycle&quot;:null}" ecos:errorCode="cr-action-plan-creating">
                <bpmn:incoming >Flow_0ftmfkk</bpmn:incoming>
                <bpmn:errorEventDefinition  errorRef="Error_Qvyz63E" id="ErrorEventDefinition_05rca9t"/>
            </bpmn:endEvent>
            <bpmn:task name="" id="Activity_1u9j3qq" ecos:documentation="{}" ecos:asyncConfig="{&quot;asyncBefore&quot;:false,&quot;asyncAfter&quot;:false,&quot;exclusive&quot;:true}" ecos:taskType="setStatus" ecos:name_ml="{}" ecos:jobConfig="{&quot;jobPriority&quot;:null,&quot;jobRetryTimeCycle&quot;:null}" ecos:status="cr-registration">
                <bpmn:incoming >Flow_1j4kz66</bpmn:incoming>
                <bpmn:outgoing >Flow_1361e1h</bpmn:outgoing>
            </bpmn:task>
            <bpmn:sequenceFlow sourceRef="Event_08y1fx0" targetRef="Activity_1u9j3qq" name="" id="Flow_1j4kz66" ecos:name_ml="{}" ecos:conditionConfig="{&quot;fn&quot;:&quot; &quot;,&quot;expression&quot;:&quot;&quot;,&quot;outcome&quot;:&quot;&quot;}" ecos:conditionType="NONE"/>
            <bpmn:sequenceFlow sourceRef="Activity_1u9j3qq" targetRef="Activity_1vca8j6" name="" id="Flow_1361e1h" ecos:name_ml="{}" ecos:conditionConfig="{&quot;fn&quot;:&quot; &quot;,&quot;expression&quot;:&quot;&quot;,&quot;outcome&quot;:&quot;&quot;}" ecos:conditionType="NONE"/>
            <bpmn:sequenceFlow sourceRef="Activity_1vca8j6" targetRef="Event_0nnj983" name="" id="Flow_0ftmfkk" ecos:name_ml="{}" ecos:conditionConfig="{&quot;fn&quot;:&quot;&quot;,&quot;expression&quot;:&quot;&quot;,&quot;outcome&quot;:&quot;&quot;}" ecos:conditionType="NONE"/>
            <bpmn:userTask name="Регистрация" id="Activity_1vca8j6" ecos:documentation="{}" ecos:manualRecipients="[]" ecos:outcomes="[{&quot;id&quot;:&quot;registered&quot;,&quot;name&quot;:{&quot;en&quot;:&quot;Registered&quot;,&quot;ru&quot;:&quot;Зарегистрировано&quot;},&quot;config&quot;:{&quot;theme&quot;:&quot;PRIMARY&quot;}}]" ecos:laEnabled="false" ecos:name_ml="{&quot;ru&quot;:&quot;Регистрация&quot;}" ecos:laNotificationType="EMAIL_NOTIFICATION" ecos:manualRecipientsMode="false" ecos:priority="MEDIUM" ecos:assignees="[&quot;registrar-role&quot;]">
                <bpmn:incoming >Flow_1361e1h</bpmn:incoming>
                <bpmn:outgoing >Flow_0ftmfkk</bpmn:outgoing>
            </bpmn:userTask>
        </bpmn:subProcess>
        <bpmn:sequenceFlow sourceRef="Event_06mr4j6" targetRef="Activity_06i9ief" name="" id="Flow_02c54hj" ecos:name_ml="{}" ecos:conditionConfig="{&quot;fn&quot;:&quot; &quot;,&quot;expression&quot;:&quot;&quot;,&quot;outcome&quot;:&quot;&quot;}" ecos:conditionType="NONE"/>
        <bpmn:boundaryEvent  cancelActivity="true" attachedToRef="Activity_06i9ief" name="" id="Event_0s0jisx" ecos:documentation="{}" ecos:asyncConfig="{&quot;asyncBefore&quot;:false,&quot;asyncAfter&quot;:false,&quot;exclusive&quot;:true}" ecos:errorName="catch-cr-action-plan-creating" ecos:name_ml="{}" ecos:jobConfig="{&quot;jobPriority&quot;:null,&quot;jobRetryTimeCycle&quot;:null}" ecos:errorCode="cr-action-plan-creating">
            <bpmn:outgoing>Flow_0a4s7bk</bpmn:outgoing>
            <bpmn:errorEventDefinition errorRef="Error_O51G2aI" id="ErrorEventDefinition_1nucq80"/>
        </bpmn:boundaryEvent>
        <bpmn:subProcess triggeredByEvent="false" name="" id="Activity_1fscgo7" ecos:documentation="{}" ecos:asyncConfig="{&quot;asyncBefore&quot;:false,&quot;asyncAfter&quot;:false,&quot;exclusive&quot;:true}" ecos:name_ml="{}" ecos:jobConfig="{&quot;jobPriority&quot;:null,&quot;jobRetryTimeCycle&quot;:null}">
            <bpmn:incoming >Flow_0a4s7bk</bpmn:incoming>
            <bpmn:startEvent isInterrupting="true" name="" id="Event_1p6qwcl" ecos:documentation="{}" ecos:asyncConfig="{&quot;asyncBefore&quot;:false,&quot;asyncAfter&quot;:false,&quot;exclusive&quot;:true}" ecos:name_ml="{}" ecos:jobConfig="{&quot;jobPriority&quot;:null,&quot;jobRetryTimeCycle&quot;:null}">
                <bpmn:outgoing >Flow_0idb7s1</bpmn:outgoing>
            </bpmn:startEvent>
            <bpmn:endEvent name="" id="Event_1xq7ezu" ecos:documentation="{}" ecos:asyncConfig="{&quot;asyncBefore&quot;:false,&quot;asyncAfter&quot;:false,&quot;exclusive&quot;:true}" ecos:errorName="cr-action-plan-approving" ecos:name_ml="{}" ecos:jobConfig="{&quot;jobPriority&quot;:null,&quot;jobRetryTimeCycle&quot;:null}" ecos:errorCode="cr-action-plan-approving">
                <bpmn:incoming >Flow_1ebzssr</bpmn:incoming>
                <bpmn:errorEventDefinition  errorRef="Error_AbdZo5Y" id="ErrorEventDefinition_0eo8ruv"/>
            </bpmn:endEvent>
            <bpmn:task name="" id="Activity_1laoi38" ecos:documentation="{}" ecos:asyncConfig="{&quot;asyncBefore&quot;:false,&quot;asyncAfter&quot;:false,&quot;exclusive&quot;:true}" ecos:taskType="setStatus" ecos:name_ml="{}" ecos:jobConfig="{&quot;jobPriority&quot;:null,&quot;jobRetryTimeCycle&quot;:null}" ecos:status="cr-action-plan-creating">
                <bpmn:incoming >Flow_0idb7s1</bpmn:incoming>
                <bpmn:outgoing >Flow_1vndndf</bpmn:outgoing>
            </bpmn:task>
            <bpmn:sequenceFlow sourceRef="Event_1p6qwcl" targetRef="Activity_1laoi38" name="" id="Flow_0idb7s1" ecos:name_ml="{}" ecos:conditionConfig="{&quot;fn&quot;:&quot; &quot;,&quot;expression&quot;:&quot;&quot;,&quot;outcome&quot;:&quot;&quot;}" ecos:conditionType="NONE"/>
            <bpmn:sequenceFlow sourceRef="Activity_1laoi38" targetRef="Activity_160zcyt" name="" id="Flow_1vndndf" ecos:name_ml="{}" ecos:conditionConfig="{&quot;fn&quot;:&quot; &quot;,&quot;expression&quot;:&quot;&quot;,&quot;outcome&quot;:&quot;&quot;}" ecos:conditionType="NONE"/>
            <bpmn:sequenceFlow sourceRef="Activity_160zcyt" targetRef="Event_1xq7ezu" name="" id="Flow_1ebzssr" ecos:name_ml="{}" ecos:conditionConfig="{&quot;fn&quot;:&quot;&quot;,&quot;expression&quot;:&quot;&quot;,&quot;outcome&quot;:&quot;&quot;}" ecos:conditionType="NONE"/>
            <bpmn:userTask name="Формирование плана мероприятий" id="Activity_160zcyt" ecos:documentation="{}" ecos:manualRecipients="[]" ecos:outcomes="[{&quot;id&quot;:&quot;done&quot;,&quot;name&quot;:{&quot;ru&quot;:&quot;Выполнено&quot;,&quot;en&quot;:&quot;Done&quot;},&quot;config&quot;:{&quot;theme&quot;:&quot;PRIMARY&quot;}}]" ecos:laEnabled="false" ecos:name_ml="{&quot;ru&quot;:&quot;Формирование плана мероприятий&quot;}" ecos:laNotificationType="EMAIL_NOTIFICATION" ecos:manualRecipientsMode="false" ecos:priority="MEDIUM" ecos:assignees="[&quot;initiator-role&quot;]">
                <bpmn:incoming >Flow_1vndndf</bpmn:incoming>
                <bpmn:outgoing >Flow_1ebzssr</bpmn:outgoing>
            </bpmn:userTask>
        </bpmn:subProcess>
        <bpmn:sequenceFlow sourceRef="Event_0s0jisx" targetRef="Activity_1fscgo7" name="" id="Flow_0a4s7bk" ecos:name_ml="{}" ecos:conditionConfig="{&quot;fn&quot;:&quot; &quot;,&quot;expression&quot;:&quot;&quot;,&quot;outcome&quot;:&quot;&quot;}" ecos:conditionType="NONE"/>
        <bpmn:subProcess triggeredByEvent="false" name="" id="Activity_1gra44f" ecos:documentation="{}" ecos:asyncConfig="{&quot;asyncBefore&quot;:false,&quot;asyncAfter&quot;:false,&quot;exclusive&quot;:true}" ecos:name_ml="{}" ecos:jobConfig="{&quot;jobPriority&quot;:null,&quot;jobRetryTimeCycle&quot;:null}">
            <bpmn:incoming >Flow_01ckbmr</bpmn:incoming>
            <bpmn:startEvent isInterrupting="true" name="" id="Event_1r2kc81" ecos:documentation="{}" ecos:asyncConfig="{&quot;asyncBefore&quot;:false,&quot;asyncAfter&quot;:false,&quot;exclusive&quot;:true}" ecos:name_ml="{}" ecos:jobConfig="{&quot;jobPriority&quot;:null,&quot;jobRetryTimeCycle&quot;:null}">
                <bpmn:outgoing >Flow_036a0dc</bpmn:outgoing>
            </bpmn:startEvent>
            <bpmn:endEvent name="" id="Event_05xa35d" ecos:documentation="{}" ecos:asyncConfig="{&quot;asyncBefore&quot;:false,&quot;asyncAfter&quot;:false,&quot;exclusive&quot;:true}" ecos:errorName="cr-assigning-commissions" ecos:name_ml="{}" ecos:jobConfig="{&quot;jobPriority&quot;:null,&quot;jobRetryTimeCycle&quot;:null}" ecos:errorCode="cr-assigning-commissions">
                <bpmn:incoming >Flow_05pka45</bpmn:incoming>
                <bpmn:errorEventDefinition  errorRef="Error_vmbm5k4" id="ErrorEventDefinition_00ms75b"/>
            </bpmn:endEvent>
            <bpmn:task name="" id="Activity_15nyuuv" ecos:documentation="{}" ecos:asyncConfig="{&quot;asyncBefore&quot;:false,&quot;asyncAfter&quot;:false,&quot;exclusive&quot;:true}" ecos:taskType="setStatus" ecos:name_ml="{}" ecos:jobConfig="{&quot;jobPriority&quot;:null,&quot;jobRetryTimeCycle&quot;:null}" ecos:status="cr-action-plan-approving">
                <bpmn:incoming >Flow_036a0dc</bpmn:incoming>
                <bpmn:outgoing >Flow_0z2dib1</bpmn:outgoing>
            </bpmn:task>
            <bpmn:sequenceFlow sourceRef="Event_1r2kc81" targetRef="Activity_15nyuuv" name="" id="Flow_036a0dc" ecos:name_ml="{}" ecos:conditionConfig="{&quot;fn&quot;:&quot; &quot;,&quot;expression&quot;:&quot;&quot;,&quot;outcome&quot;:&quot;&quot;}" ecos:conditionType="NONE"/>
            <bpmn:sequenceFlow sourceRef="Activity_15nyuuv" targetRef="Activity_168xhbo" name="" id="Flow_0z2dib1" ecos:name_ml="{}" ecos:conditionConfig="{&quot;fn&quot;:&quot; &quot;,&quot;expression&quot;:&quot;&quot;,&quot;outcome&quot;:&quot;&quot;}" ecos:conditionType="NONE"/>
            <bpmn:sequenceFlow sourceRef="Activity_168xhbo" targetRef="Event_05xa35d" name="" id="Flow_05pka45" ecos:name_ml="{}" ecos:conditionConfig="{&quot;fn&quot;:&quot;&quot;,&quot;expression&quot;:&quot;&quot;,&quot;outcome&quot;:&quot;&quot;}" ecos:conditionType="NONE"/>
            <bpmn:userTask name="Согласование плана мероприятий" id="Activity_168xhbo" ecos:documentation="{}" ecos:manualRecipients="[]" ecos:outcomes="[{&quot;id&quot;:&quot;approved&quot;,&quot;name&quot;:{&quot;ru&quot;:&quot;Согласовано&quot;,&quot;en&quot;:&quot;Approved&quot;},&quot;config&quot;:{&quot;theme&quot;:&quot;PRIMARY&quot;}}]" ecos:laEnabled="false" ecos:name_ml="{&quot;ru&quot;:&quot;Согласование плана мероприятий&quot;}" ecos:laNotificationType="EMAIL_NOTIFICATION" ecos:manualRecipientsMode="false" ecos:priority="MEDIUM" ecos:multiInstanceConfig="{&quot;sequential&quot;:false,&quot;collection&quot;:&quot;&quot;,&quot;element&quot;:&quot;&quot;,&quot;loopCardinality&quot;:&quot;&quot;,&quot;completionCondition&quot;:&quot;&quot;,&quot;asyncConfig&quot;:{&quot;asyncBefore&quot;:false,&quot;asyncAfter&quot;:false,&quot;exclusive&quot;:true},&quot;jobConfig&quot;:{&quot;jobPriority&quot;:null,&quot;jobRetryTimeCycle&quot;:&quot;&quot;}}" ecos:assignees="[&quot;expert-team-role&quot;]">
                <bpmn:incoming >Flow_0z2dib1</bpmn:incoming>
                <bpmn:outgoing >Flow_05pka45</bpmn:outgoing>
                <bpmn:multiInstanceLoopCharacteristics isSequential="false" camunda:asyncBefore="false" camunda:exclusive="true" camunda:asyncAfter="false">
                    <bpmn:extensionElements/>
                </bpmn:multiInstanceLoopCharacteristics>
            </bpmn:userTask>
        </bpmn:subProcess>
        <bpmn:subProcess triggeredByEvent="false" name="" id="Activity_1ctkomf" ecos:documentation="{}" ecos:asyncConfig="{&quot;asyncBefore&quot;:false,&quot;asyncAfter&quot;:false,&quot;exclusive&quot;:true}" ecos:name_ml="{}" ecos:jobConfig="{&quot;jobPriority&quot;:null,&quot;jobRetryTimeCycle&quot;:null}">
            <bpmn:incoming >Flow_0x8q0t7</bpmn:incoming>
            <bpmn:startEvent isInterrupting="true" name="" id="Event_18ex763" ecos:documentation="{}" ecos:asyncConfig="{&quot;asyncBefore&quot;:false,&quot;asyncAfter&quot;:false,&quot;exclusive&quot;:true}" ecos:name_ml="{}" ecos:jobConfig="{&quot;jobPriority&quot;:null,&quot;jobRetryTimeCycle&quot;:null}">
                <bpmn:outgoing >Flow_04qhbvg</bpmn:outgoing>
            </bpmn:startEvent>
            <bpmn:endEvent name="" id="Event_048d9vp" ecos:documentation="{}" ecos:asyncConfig="{&quot;asyncBefore&quot;:false,&quot;asyncAfter&quot;:false,&quot;exclusive&quot;:true}" ecos:errorName="cr-acceptance" ecos:name_ml="{}" ecos:jobConfig="{&quot;jobPriority&quot;:null,&quot;jobRetryTimeCycle&quot;:null}" ecos:errorCode="cr-acceptance">
                <bpmn:incoming >Flow_0v5cyqg</bpmn:incoming>
                <bpmn:errorEventDefinition  errorRef="Error_MtGTrqk" id="ErrorEventDefinition_1hy4rpi"/>
            </bpmn:endEvent>
            <bpmn:task name="" id="Activity_0lurpn9" ecos:documentation="{}" ecos:asyncConfig="{&quot;asyncBefore&quot;:false,&quot;asyncAfter&quot;:false,&quot;exclusive&quot;:true}" ecos:taskType="setStatus" ecos:name_ml="{}" ecos:jobConfig="{&quot;jobPriority&quot;:null,&quot;jobRetryTimeCycle&quot;:null}" ecos:status="cr-assigning-commissions">
                <bpmn:incoming >Flow_04qhbvg</bpmn:incoming>
                <bpmn:outgoing >Flow_1vroye7</bpmn:outgoing>
            </bpmn:task>
            <bpmn:sequenceFlow sourceRef="Event_18ex763" targetRef="Activity_0lurpn9" name="" id="Flow_04qhbvg" ecos:name_ml="{}" ecos:conditionConfig="{&quot;fn&quot;:&quot; &quot;,&quot;expression&quot;:&quot;&quot;,&quot;outcome&quot;:&quot;&quot;}" ecos:conditionType="NONE"/>
            <bpmn:sequenceFlow sourceRef="Activity_0lurpn9" targetRef="Activity_0srzvps" name="" id="Flow_1vroye7" ecos:name_ml="{}" ecos:conditionConfig="{&quot;fn&quot;:&quot; &quot;,&quot;expression&quot;:&quot;&quot;,&quot;outcome&quot;:&quot;&quot;}" ecos:conditionType="NONE"/>
            <bpmn:sequenceFlow sourceRef="Activity_0srzvps" targetRef="Event_048d9vp" name="" id="Flow_0v5cyqg" ecos:name_ml="{}" ecos:conditionConfig="{&quot;fn&quot;:&quot;&quot;,&quot;expression&quot;:&quot;&quot;,&quot;outcome&quot;:&quot;&quot;}" ecos:conditionType="NONE"/>
            <bpmn:userTask name="Назначение поручений" id="Activity_0srzvps" ecos:documentation="{}" ecos:manualRecipients="[]" ecos:outcomes="[{&quot;id&quot;:&quot;done&quot;,&quot;name&quot;:{&quot;ru&quot;:&quot;Выполнено&quot;,&quot;en&quot;:&quot;Done&quot;},&quot;config&quot;:{&quot;theme&quot;:&quot;PRIMARY&quot;}}]" ecos:laEnabled="false" ecos:name_ml="{&quot;ru&quot;:&quot;Назначение поручений&quot;}" ecos:laNotificationType="EMAIL_NOTIFICATION" ecos:manualRecipientsMode="false" ecos:priority="MEDIUM" ecos:assignees="[&quot;department-leader-role&quot;]">
                <bpmn:incoming >Flow_1vroye7</bpmn:incoming>
                <bpmn:outgoing >Flow_0v5cyqg</bpmn:outgoing>
            </bpmn:userTask>
        </bpmn:subProcess>
        <bpmn:subProcess triggeredByEvent="false" name="" id="Activity_1gpw3kp" ecos:documentation="{}" ecos:asyncConfig="{&quot;asyncBefore&quot;:false,&quot;asyncAfter&quot;:false,&quot;exclusive&quot;:true}" ecos:name_ml="{}" ecos:jobConfig="{&quot;jobPriority&quot;:null,&quot;jobRetryTimeCycle&quot;:null}">
            <bpmn:incoming >Flow_11bvkd6</bpmn:incoming>
            <bpmn:startEvent isInterrupting="true" name="" id="Event_109homn" ecos:documentation="{}" ecos:asyncConfig="{&quot;asyncBefore&quot;:false,&quot;asyncAfter&quot;:false,&quot;exclusive&quot;:true}" ecos:name_ml="{}" ecos:jobConfig="{&quot;jobPriority&quot;:null,&quot;jobRetryTimeCycle&quot;:null}">
                <bpmn:outgoing >Flow_12asyv0</bpmn:outgoing>
            </bpmn:startEvent>
            <bpmn:endEvent name="" id="Event_1fddm07" ecos:documentation="{}" ecos:asyncConfig="{&quot;asyncBefore&quot;:false,&quot;asyncAfter&quot;:false,&quot;exclusive&quot;:true}" ecos:errorName="cr-evaluation" ecos:name_ml="{}" ecos:jobConfig="{&quot;jobPriority&quot;:null,&quot;jobRetryTimeCycle&quot;:null}" ecos:errorCode="cr-evaluation">
                <bpmn:incoming >Flow_0teseho</bpmn:incoming>
                <bpmn:errorEventDefinition  errorRef="Error_VTNa8Ox" id="ErrorEventDefinition_19ob08t"/>
            </bpmn:endEvent>
            <bpmn:task name="" id="Activity_0sy4ge9" ecos:documentation="{}" ecos:asyncConfig="{&quot;asyncBefore&quot;:false,&quot;asyncAfter&quot;:false,&quot;exclusive&quot;:true}" ecos:taskType="setStatus" ecos:name_ml="{}" ecos:jobConfig="{&quot;jobPriority&quot;:null,&quot;jobRetryTimeCycle&quot;:null}" ecos:status="cr-acceptance">
                <bpmn:incoming >Flow_12asyv0</bpmn:incoming>
                <bpmn:outgoing >Flow_1c2qcd8</bpmn:outgoing>
            </bpmn:task>
            <bpmn:sequenceFlow sourceRef="Event_109homn" targetRef="Activity_0sy4ge9" name="" id="Flow_12asyv0" ecos:name_ml="{}" ecos:conditionConfig="{&quot;fn&quot;:&quot; &quot;,&quot;expression&quot;:&quot;&quot;,&quot;outcome&quot;:&quot;&quot;}" ecos:conditionType="NONE"/>
            <bpmn:sequenceFlow sourceRef="Activity_0sy4ge9" targetRef="Activity_1eti6dl" name="" id="Flow_1c2qcd8" ecos:name_ml="{}" ecos:conditionConfig="{&quot;fn&quot;:&quot; &quot;,&quot;expression&quot;:&quot;&quot;,&quot;outcome&quot;:&quot;&quot;}" ecos:conditionType="NONE"/>
            <bpmn:sequenceFlow sourceRef="Activity_1eti6dl" targetRef="Event_1fddm07" name="" id="Flow_0teseho" ecos:name_ml="{}" ecos:conditionConfig="{&quot;fn&quot;:&quot; &quot;,&quot;expression&quot;:&quot;&quot;,&quot;outcome&quot;:&quot;&quot;}" ecos:conditionType="NONE"/>
            <bpmn:userTask name="Приемка" id="Activity_1eti6dl" ecos:documentation="{}" ecos:manualRecipients="[]" ecos:outcomes="[{&quot;id&quot;:&quot;done&quot;,&quot;name&quot;:{&quot;ru&quot;:&quot;Выполнено&quot;,&quot;en&quot;:&quot;Done&quot;},&quot;config&quot;:{&quot;theme&quot;:&quot;PRIMARY&quot;}}]" ecos:laEnabled="false" ecos:name_ml="{&quot;ru&quot;:&quot;Приемка&quot;}" ecos:laNotificationType="EMAIL_NOTIFICATION" ecos:manualRecipientsMode="false" ecos:priority="MEDIUM" ecos:assignees="[&quot;department-leader-role&quot;]">
                <bpmn:incoming >Flow_1c2qcd8</bpmn:incoming>
                <bpmn:outgoing >Flow_0teseho</bpmn:outgoing>
            </bpmn:userTask>
        </bpmn:subProcess>
        <bpmn:subProcess triggeredByEvent="false" name="" id="Activity_17pdmja" ecos:documentation="{}" ecos:asyncConfig="{&quot;asyncBefore&quot;:false,&quot;asyncAfter&quot;:false,&quot;exclusive&quot;:true}" ecos:name_ml="{}" ecos:jobConfig="{&quot;jobPriority&quot;:null,&quot;jobRetryTimeCycle&quot;:null}">
            <bpmn:incoming >Flow_0s4x984</bpmn:incoming>
            <bpmn:startEvent isInterrupting="true" name="" id="Event_0x9jiwi" ecos:documentation="{}" ecos:asyncConfig="{&quot;asyncBefore&quot;:false,&quot;asyncAfter&quot;:false,&quot;exclusive&quot;:true}" ecos:name_ml="{}" ecos:jobConfig="{&quot;jobPriority&quot;:null,&quot;jobRetryTimeCycle&quot;:null}">
                <bpmn:outgoing >Flow_0fkyri9</bpmn:outgoing>
            </bpmn:startEvent>
            <bpmn:endEvent name="" id="Event_0xfzeiu" ecos:documentation="{}" ecos:asyncConfig="{&quot;asyncBefore&quot;:false,&quot;asyncAfter&quot;:false,&quot;exclusive&quot;:true}" ecos:errorName="cr-complete" ecos:name_ml="{}" ecos:jobConfig="{&quot;jobPriority&quot;:null,&quot;jobRetryTimeCycle&quot;:null}" ecos:errorCode="cr-complete">
                <bpmn:incoming >Flow_1fdo9or</bpmn:incoming>
                <bpmn:errorEventDefinition  errorRef="Error_pRioQIX" id="ErrorEventDefinition_10ldaq6"/>
            </bpmn:endEvent>
            <bpmn:task name="" id="Activity_0j3imc7" ecos:documentation="{}" ecos:asyncConfig="{&quot;asyncBefore&quot;:false,&quot;asyncAfter&quot;:false,&quot;exclusive&quot;:true}" ecos:taskType="setStatus" ecos:name_ml="{}" ecos:jobConfig="{&quot;jobPriority&quot;:null,&quot;jobRetryTimeCycle&quot;:null}" ecos:status="cr-evaluation">
                <bpmn:incoming >Flow_0fkyri9</bpmn:incoming>
                <bpmn:outgoing >Flow_088i6hx</bpmn:outgoing>
            </bpmn:task>
            <bpmn:sequenceFlow sourceRef="Event_0x9jiwi" targetRef="Activity_0j3imc7" name="" id="Flow_0fkyri9" ecos:name_ml="{}" ecos:conditionConfig="{&quot;fn&quot;:&quot; &quot;,&quot;expression&quot;:&quot;&quot;,&quot;outcome&quot;:&quot;&quot;}" ecos:conditionType="NONE"/>
            <bpmn:sequenceFlow sourceRef="Activity_0j3imc7" targetRef="Activity_0npdb6z" name="" id="Flow_088i6hx" ecos:name_ml="{}" ecos:conditionConfig="{&quot;fn&quot;:&quot; &quot;,&quot;expression&quot;:&quot;&quot;,&quot;outcome&quot;:&quot;&quot;}" ecos:conditionType="NONE"/>
            <bpmn:sequenceFlow sourceRef="Activity_0npdb6z" targetRef="Event_0xfzeiu" name="" id="Flow_1fdo9or" ecos:name_ml="{}" ecos:conditionConfig="{&quot;fn&quot;:&quot;&quot;,&quot;expression&quot;:&quot;&quot;,&quot;outcome&quot;:&quot;&quot;}" ecos:conditionType="NONE"/>
            <bpmn:userTask name="Оценка" id="Activity_0npdb6z" ecos:documentation="{}" ecos:manualRecipients="[]" ecos:outcomes="[{&quot;id&quot;:&quot;done&quot;,&quot;name&quot;:{&quot;ru&quot;:&quot;Выполнено&quot;,&quot;en&quot;:&quot;Done&quot;},&quot;config&quot;:{&quot;theme&quot;:&quot;PRIMARY&quot;}}]" ecos:laEnabled="false" ecos:name_ml="{&quot;ru&quot;:&quot;Оценка&quot;}" ecos:laNotificationType="EMAIL_NOTIFICATION" ecos:manualRecipientsMode="false" ecos:priority="MEDIUM" ecos:multiInstanceConfig="{&quot;sequential&quot;:false,&quot;collection&quot;:&quot;&quot;,&quot;element&quot;:&quot;&quot;,&quot;loopCardinality&quot;:&quot;&quot;,&quot;completionCondition&quot;:&quot;&quot;,&quot;asyncConfig&quot;:{&quot;asyncBefore&quot;:false,&quot;asyncAfter&quot;:false,&quot;exclusive&quot;:true},&quot;jobConfig&quot;:{&quot;jobPriority&quot;:null,&quot;jobRetryTimeCycle&quot;:&quot;&quot;}}" ecos:assignees="[&quot;expert-team-role&quot;]">
                <bpmn:incoming >Flow_088i6hx</bpmn:incoming>
                <bpmn:outgoing >Flow_1fdo9or</bpmn:outgoing>
                <bpmn:multiInstanceLoopCharacteristics isSequential="false" camunda:asyncBefore="false" camunda:exclusive="true" camunda:asyncAfter="false">
                    <bpmn:extensionElements/>
                </bpmn:multiInstanceLoopCharacteristics>
            </bpmn:userTask>
        </bpmn:subProcess>
        <bpmn:subProcess triggeredByEvent="false" name="" id="Activity_0xh1h4u" ecos:documentation="{}" ecos:asyncConfig="{&quot;asyncBefore&quot;:false,&quot;asyncAfter&quot;:false,&quot;exclusive&quot;:true}" ecos:name_ml="{}" ecos:jobConfig="{&quot;jobPriority&quot;:null,&quot;jobRetryTimeCycle&quot;:null}">
            <bpmn:incoming >Flow_0aq2usr</bpmn:incoming>
            <bpmn:startEvent isInterrupting="true" name="" id="Event_1l4ixtw" ecos:documentation="{}" ecos:asyncConfig="{&quot;asyncBefore&quot;:false,&quot;asyncAfter&quot;:false,&quot;exclusive&quot;:true}" ecos:name_ml="{}" ecos:jobConfig="{&quot;jobPriority&quot;:null,&quot;jobRetryTimeCycle&quot;:null}">
                <bpmn:outgoing >Flow_1fxj829</bpmn:outgoing>
            </bpmn:startEvent>
            <bpmn:endEvent name="" id="Event_0osbixb" ecos:documentation="{}" ecos:asyncConfig="{&quot;asyncBefore&quot;:false,&quot;asyncAfter&quot;:false,&quot;exclusive&quot;:true}" ecos:errorName="cr-end" ecos:name_ml="{}" ecos:jobConfig="{&quot;jobPriority&quot;:null,&quot;jobRetryTimeCycle&quot;:null}" ecos:errorCode="cr-end">
                <bpmn:incoming >Flow_0g1jr88</bpmn:incoming>
                <bpmn:errorEventDefinition  errorRef="Error_d8dOZGH" id="ErrorEventDefinition_1df7psp"/>
            </bpmn:endEvent>
            <bpmn:task name="" id="Activity_144o4zz" ecos:documentation="{}" ecos:asyncConfig="{&quot;asyncBefore&quot;:false,&quot;asyncAfter&quot;:false,&quot;exclusive&quot;:true}" ecos:taskType="setStatus" ecos:name_ml="{}" ecos:jobConfig="{&quot;jobPriority&quot;:null,&quot;jobRetryTimeCycle&quot;:null}" ecos:status="cr-complete">
                <bpmn:incoming >Flow_1fxj829</bpmn:incoming>
                <bpmn:outgoing >Flow_0g1jr88</bpmn:outgoing>
            </bpmn:task>
            <bpmn:sequenceFlow sourceRef="Event_1l4ixtw" targetRef="Activity_144o4zz" name="" id="Flow_1fxj829" ecos:name_ml="{}" ecos:conditionConfig="{&quot;fn&quot;:&quot; &quot;,&quot;expression&quot;:&quot;&quot;,&quot;outcome&quot;:&quot;&quot;}" ecos:conditionType="NONE"/>
            <bpmn:sequenceFlow sourceRef="Activity_144o4zz" targetRef="Event_0osbixb" name="" id="Flow_0g1jr88" ecos:name_ml="{}" ecos:conditionConfig="{&quot;fn&quot;:&quot; &quot;,&quot;expression&quot;:&quot;&quot;,&quot;outcome&quot;:&quot;&quot;}" ecos:conditionType="NONE"/>
        </bpmn:subProcess>
        <bpmn:boundaryEvent  cancelActivity="true" attachedToRef="Activity_0xh1h4u" name="" id="Event_10a8nju" ecos:documentation="{}" ecos:asyncConfig="{&quot;asyncBefore&quot;:false,&quot;asyncAfter&quot;:false,&quot;exclusive&quot;:true}" ecos:errorName="catch-cr-end" ecos:name_ml="{}" ecos:jobConfig="{&quot;jobPriority&quot;:null,&quot;jobRetryTimeCycle&quot;:null}" ecos:errorCode="cr-end">
            <bpmn:outgoing>Flow_1rhkg15</bpmn:outgoing>
            <bpmn:errorEventDefinition errorRef="Error_PzCJ5QG" id="ErrorEventDefinition_1e1e45e"/>
        </bpmn:boundaryEvent>
        <bpmn:sequenceFlow sourceRef="Event_10a8nju" targetRef="Event_1xysdvv" name="" id="Flow_1rhkg15" ecos:name_ml="{}" ecos:conditionConfig="{&quot;fn&quot;:&quot; &quot;,&quot;expression&quot;:&quot;&quot;,&quot;outcome&quot;:&quot;&quot;}" ecos:conditionType="NONE"/>
        <bpmn:boundaryEvent  cancelActivity="true" attachedToRef="Activity_1fscgo7" name="" id="Event_1tijolq" ecos:documentation="{}" ecos:asyncConfig="{&quot;asyncBefore&quot;:false,&quot;asyncAfter&quot;:false,&quot;exclusive&quot;:true}" ecos:errorName="catch-cr-action-plan-approving" ecos:name_ml="{}" ecos:jobConfig="{&quot;jobPriority&quot;:null,&quot;jobRetryTimeCycle&quot;:null}" ecos:errorCode="cr-action-plan-approving">
            <bpmn:outgoing>Flow_01ckbmr</bpmn:outgoing>
            <bpmn:errorEventDefinition errorRef="Error_Vdyi6Ld" id="ErrorEventDefinition_0vvqwgm"/>
        </bpmn:boundaryEvent>
        <bpmn:sequenceFlow sourceRef="Event_1tijolq" targetRef="Activity_1gra44f" name="" id="Flow_01ckbmr" ecos:name_ml="{}" ecos:conditionConfig="{&quot;fn&quot;:&quot; &quot;,&quot;expression&quot;:&quot;&quot;,&quot;outcome&quot;:&quot;&quot;}" ecos:conditionType="NONE"/>
        <bpmn:sequenceFlow sourceRef="Event_0qrvcf0" targetRef="Activity_1ctkomf" name="" id="Flow_0x8q0t7" ecos:name_ml="{}" ecos:conditionConfig="{&quot;fn&quot;:&quot; &quot;,&quot;expression&quot;:&quot;&quot;,&quot;outcome&quot;:&quot;&quot;}" ecos:conditionType="NONE"/>
        <bpmn:boundaryEvent  cancelActivity="true" attachedToRef="Activity_17pdmja" name="" id="Event_0yga7lj" ecos:documentation="{}" ecos:asyncConfig="{&quot;asyncBefore&quot;:false,&quot;asyncAfter&quot;:false,&quot;exclusive&quot;:true}" ecos:errorName="catch-cr-complete" ecos:name_ml="{}" ecos:jobConfig="{&quot;jobPriority&quot;:null,&quot;jobRetryTimeCycle&quot;:null}" ecos:errorCode="cr-complete">
            <bpmn:outgoing>Flow_0aq2usr</bpmn:outgoing>
            <bpmn:errorEventDefinition errorRef="Error_vI7FaoI" id="ErrorEventDefinition_1pifrty"/>
        </bpmn:boundaryEvent>
        <bpmn:boundaryEvent  cancelActivity="true" attachedToRef="Activity_1gra44f" name="" id="Event_0qrvcf0" ecos:documentation="{}" ecos:asyncConfig="{&quot;asyncBefore&quot;:false,&quot;asyncAfter&quot;:false,&quot;exclusive&quot;:true}" ecos:errorName="catch-cr-assigning-commissions" ecos:name_ml="{}" ecos:jobConfig="{&quot;jobPriority&quot;:null,&quot;jobRetryTimeCycle&quot;:null}" ecos:errorCode="cr-assigning-commissions">
            <bpmn:outgoing>Flow_0x8q0t7</bpmn:outgoing>
            <bpmn:errorEventDefinition errorRef="Error_dU1PO8P" id="ErrorEventDefinition_0yntocu"/>
        </bpmn:boundaryEvent>
        <bpmn:boundaryEvent  cancelActivity="true" attachedToRef="Activity_1ctkomf" name="" id="Event_1svc0dc" ecos:documentation="{}" ecos:asyncConfig="{&quot;asyncBefore&quot;:false,&quot;asyncAfter&quot;:false,&quot;exclusive&quot;:true}" ecos:errorName="catch-cr-acceptance" ecos:name_ml="{}" ecos:jobConfig="{&quot;jobPriority&quot;:null,&quot;jobRetryTimeCycle&quot;:null}" ecos:errorCode="cr-acceptance">
            <bpmn:outgoing>Flow_11bvkd6</bpmn:outgoing>
            <bpmn:errorEventDefinition errorRef="Error_fR1bCnT" id="ErrorEventDefinition_1143xph"/>
        </bpmn:boundaryEvent>
        <bpmn:sequenceFlow sourceRef="Event_1svc0dc" targetRef="Activity_1gpw3kp" name="" id="Flow_11bvkd6" ecos:name_ml="{}" ecos:conditionConfig="{&quot;fn&quot;:&quot; &quot;,&quot;expression&quot;:&quot;&quot;,&quot;outcome&quot;:&quot;&quot;}" ecos:conditionType="NONE"/>
        <bpmn:sequenceFlow sourceRef="Event_011de9s" targetRef="Activity_17pdmja" name="" id="Flow_0s4x984" ecos:name_ml="{}" ecos:conditionConfig="{&quot;fn&quot;:&quot; &quot;,&quot;expression&quot;:&quot;&quot;,&quot;outcome&quot;:&quot;&quot;}" ecos:conditionType="NONE"/>
        <bpmn:sequenceFlow sourceRef="Event_0yga7lj" targetRef="Activity_0xh1h4u" name="" id="Flow_0aq2usr" ecos:name_ml="{}" ecos:conditionConfig="{&quot;fn&quot;:&quot; &quot;,&quot;expression&quot;:&quot;&quot;,&quot;outcome&quot;:&quot;&quot;}" ecos:conditionType="NONE"/>
        <bpmn:boundaryEvent  cancelActivity="true" attachedToRef="Activity_1gpw3kp" name="" id="Event_011de9s" ecos:documentation="{}" ecos:asyncConfig="{&quot;asyncBefore&quot;:false,&quot;asyncAfter&quot;:false,&quot;exclusive&quot;:true}" ecos:errorName="catch-cr-evaluation" ecos:name_ml="{}" ecos:jobConfig="{&quot;jobPriority&quot;:null,&quot;jobRetryTimeCycle&quot;:null}" ecos:errorCode="cr-evaluation">
            <bpmn:outgoing>Flow_0s4x984</bpmn:outgoing>
            <bpmn:errorEventDefinition errorRef="Error_V5BJlxH" id="ErrorEventDefinition_1t3kayy"/>
        </bpmn:boundaryEvent>
        <bpmn:sequenceFlow sourceRef="StartEvent_1ew9rff" targetRef="Gateway_0otd8dt" name="" id="Flow_18gcg86" ecos:name_ml="{}" ecos:conditionConfig="{&quot;fn&quot;:&quot; &quot;,&quot;expression&quot;:&quot;&quot;,&quot;outcome&quot;:&quot;&quot;}" ecos:conditionType="NONE"/>
        <bpmn:subProcess triggeredByEvent="false" name="" id="Activity_1yfuswa" ecos:documentation="{}" ecos:asyncConfig="{&quot;asyncBefore&quot;:false,&quot;asyncAfter&quot;:false,&quot;exclusive&quot;:true}" ecos:name_ml="{}" ecos:jobConfig="{&quot;jobPriority&quot;:null,&quot;jobRetryTimeCycle&quot;:null}">
            <bpmn:incoming >Flow_0bgvb9h</bpmn:incoming>
            <bpmn:startEvent isInterrupting="true" name="" id="Event_0sgpzpt" ecos:documentation="{}" ecos:asyncConfig="{&quot;asyncBefore&quot;:false,&quot;asyncAfter&quot;:false,&quot;exclusive&quot;:true}" ecos:name_ml="{}" ecos:jobConfig="{&quot;jobPriority&quot;:null,&quot;jobRetryTimeCycle&quot;:null}">
                <bpmn:outgoing >Flow_1vp2jsr</bpmn:outgoing>
            </bpmn:startEvent>
            <bpmn:sequenceFlow sourceRef="Event_0sgpzpt" targetRef="Activity_075hi0s" name="" id="Flow_1vp2jsr" ecos:name_ml="{}" ecos:conditionConfig="{&quot;fn&quot;:&quot; &quot;,&quot;expression&quot;:&quot;&quot;,&quot;outcome&quot;:&quot;&quot;}" ecos:conditionType="NONE"/>
            <bpmn:sequenceFlow sourceRef="Activity_02fa1v5" targetRef="Event_1k1zw31" name="" id="Flow_1xiia3h" ecos:name_ml="{}" ecos:conditionConfig="{&quot;fn&quot;:&quot; &quot;,&quot;expression&quot;:&quot;&quot;,&quot;outcome&quot;:&quot;&quot;}" ecos:conditionType="NONE"/>
            <bpmn:task name="" id="Activity_075hi0s" ecos:documentation="{}" ecos:asyncConfig="{&quot;asyncBefore&quot;:false,&quot;asyncAfter&quot;:false,&quot;exclusive&quot;:true}" ecos:taskType="setStatus" ecos:name_ml="{}" ecos:jobConfig="{&quot;jobPriority&quot;:null,&quot;jobRetryTimeCycle&quot;:null}" ecos:status="cr-rework">
                <bpmn:incoming >Flow_1vp2jsr</bpmn:incoming>
                <bpmn:outgoing >Flow_1dpcxo0</bpmn:outgoing>
            </bpmn:task>
            <bpmn:sequenceFlow sourceRef="Activity_075hi0s" targetRef="Activity_02fa1v5" name="" id="Flow_1dpcxo0" ecos:name_ml="{}" ecos:conditionConfig="{&quot;fn&quot;:&quot;&quot;,&quot;expression&quot;:&quot;&quot;,&quot;outcome&quot;:&quot;&quot;}" ecos:conditionType="NONE"/>
            <bpmn:userTask name="Доработка" id="Activity_02fa1v5" ecos:documentation="{}" ecos:manualRecipients="[]" ecos:outcomes="[{&quot;id&quot;:&quot;done&quot;,&quot;name&quot;:{&quot;ru&quot;:&quot;Выполнено&quot;,&quot;en&quot;:&quot;Done&quot;},&quot;config&quot;:{&quot;theme&quot;:&quot;PRIMARY&quot;}}]" ecos:laEnabled="false" ecos:name_ml="{&quot;ru&quot;:&quot;Доработка&quot;}" ecos:laNotificationType="EMAIL_NOTIFICATION" ecos:manualRecipientsMode="false" ecos:priority="MEDIUM" ecos:assignees="[&quot;initiator-role&quot;]">
                <bpmn:incoming >Flow_1dpcxo0</bpmn:incoming>
                <bpmn:outgoing >Flow_1xiia3h</bpmn:outgoing>
            </bpmn:userTask>
            <bpmn:endEvent name="" id="Event_1k1zw31" ecos:documentation="{}" ecos:asyncConfig="{&quot;asyncBefore&quot;:false,&quot;asyncAfter&quot;:false,&quot;exclusive&quot;:true}" ecos:errorName="cr-rework-done" ecos:name_ml="{}" ecos:jobConfig="{&quot;jobPriority&quot;:null,&quot;jobRetryTimeCycle&quot;:null}" ecos:errorCode="cr-rework-done">
                <bpmn:incoming >Flow_1xiia3h</bpmn:incoming>
                <bpmn:errorEventDefinition  errorRef="Error_3IjV8uD" id="ErrorEventDefinition_1u7rkmi"/>
            </bpmn:endEvent>
        </bpmn:subProcess>
        <bpmn:boundaryEvent  cancelActivity="true" attachedToRef="Activity_1orn22c" name="" id="Event_19qlw14" ecos:documentation="{}" ecos:asyncConfig="{&quot;asyncBefore&quot;:false,&quot;asyncAfter&quot;:false,&quot;exclusive&quot;:true}" ecos:errorName="catch-cr-rework" ecos:name_ml="{}" ecos:jobConfig="{&quot;jobPriority&quot;:null,&quot;jobRetryTimeCycle&quot;:null}" ecos:errorCode="cr-rework">
            <bpmn:outgoing>Flow_0bgvb9h</bpmn:outgoing>
            <bpmn:errorEventDefinition errorRef="Error_OwVghIq" id="ErrorEventDefinition_0oj7vb8"/>
        </bpmn:boundaryEvent>
        <bpmn:sequenceFlow sourceRef="Event_19qlw14" targetRef="Activity_1yfuswa" name="" id="Flow_0bgvb9h" ecos:name_ml="{}" ecos:conditionConfig="{&quot;fn&quot;:&quot; &quot;,&quot;expression&quot;:&quot;&quot;,&quot;outcome&quot;:&quot;&quot;}" ecos:conditionType="NONE"/>
        <bpmn:sequenceFlow sourceRef="Gateway_0otd8dt" targetRef="Activity_1orn22c" name="" id="Flow_1wl760w" ecos:name_ml="{}" ecos:conditionConfig="{&quot;fn&quot;:&quot;&quot;,&quot;expression&quot;:&quot;&quot;,&quot;outcome&quot;:&quot;&quot;}" ecos:conditionType="NONE"/>
        <bpmn:inclusiveGateway name="" id="Gateway_0otd8dt" ecos:documentation="{}" ecos:name_ml="{}">
            <bpmn:incoming >Flow_18gcg86</bpmn:incoming>
            <bpmn:incoming >Flow_0lbo43z</bpmn:incoming>
            <bpmn:outgoing >Flow_1wl760w</bpmn:outgoing>
        </bpmn:inclusiveGateway>
        <bpmn:boundaryEvent  cancelActivity="true" attachedToRef="Activity_1yfuswa" name="" id="Event_02txiu1" ecos:documentation="{}" ecos:asyncConfig="{&quot;asyncBefore&quot;:false,&quot;asyncAfter&quot;:false,&quot;exclusive&quot;:true}" ecos:errorName="catch-cr-rework-done" ecos:name_ml="{}" ecos:jobConfig="{&quot;jobPriority&quot;:null,&quot;jobRetryTimeCycle&quot;:null}" ecos:errorCode="cr-rework-done">
            <bpmn:outgoing>Flow_0lbo43z</bpmn:outgoing>
            <bpmn:errorEventDefinition errorRef="Error_KslDkOi" id="ErrorEventDefinition_084qdbx"/>
        </bpmn:boundaryEvent>
        <bpmn:sequenceFlow sourceRef="Event_02txiu1" targetRef="Gateway_0otd8dt" name="" id="Flow_0lbo43z" ecos:name_ml="{}" ecos:conditionConfig="{&quot;fn&quot;:&quot; &quot;,&quot;expression&quot;:&quot;&quot;,&quot;outcome&quot;:&quot;&quot;}" ecos:conditionType="NONE"/>
    </bpmn:process>
    <bpmn:error name="cr-checking" id="Error_3Sl7lFV"/>
    <bpmn:error name="cr-rework" id="Error_ODErKks"/>
    <bpmn:error name="catch-cr-checking" id="Error_Fuw42ho"/>
    <bpmn:error name="cr-registration" id="Error_opWhdMs"/>
    <bpmn:error name="catch-cr-registration" id="Error_sB2Nnjm"/>
    <bpmn:error name="cr-action-plan-creating" id="Error_Qvyz63E"/>
    <bpmn:error name="catch-cr-action-plan-creating" id="Error_O51G2aI"/>
    <bpmn:error name="cr-action-plan-approving" id="Error_AbdZo5Y"/>
    <bpmn:error name="cr-assigning-commissions" id="Error_vmbm5k4"/>
    <bpmn:error name="cr-acceptance" id="Error_MtGTrqk"/>
    <bpmn:error name="cr-evaluation" id="Error_VTNa8Ox"/>
    <bpmn:error name="cr-complete" id="Error_pRioQIX"/>
    <bpmn:error name="cr-end" id="Error_d8dOZGH"/>
    <bpmn:error name="catch-cr-end" id="Error_PzCJ5QG"/>
    <bpmn:error name="catch-cr-action-plan-approving" id="Error_Vdyi6Ld"/>
    <bpmn:error name="catch-cr-complete" id="Error_vI7FaoI"/>
    <bpmn:error name="catch-cr-assigning-commissions" id="Error_dU1PO8P"/>
    <bpmn:error name="catch-cr-acceptance" id="Error_fR1bCnT"/>
    <bpmn:error name="catch-cr-evaluation" id="Error_V5BJlxH"/>
    <bpmn:error name="cr-rework-done" id="Error_3IjV8uD"/>
    <bpmn:error name="catch-cr-rework" id="Error_OwVghIq"/>
    <bpmn:error name="catch-cr-rework-done" id="Error_KslDkOi"/>
    <bpmndi:BPMNDiagram id="BPMNDiagram_1">
        <bpmndi:BPMNPlane  bpmnElement="change-request-process" id="BPMNPlane_1">
            <bpmndi:BPMNShape bpmnElement="StartEvent_1ew9rff" isExpanded="true" id="_BPMNShape_StartEvent_2">
                <dc:Bounds x="152.0" y="-128.0" width="36.0" height="36.0"/>
            </bpmndi:BPMNShape>
            <bpmndi:BPMNShape bpmnElement="Event_1xysdvv" isExpanded="true" id="Event_1xysdvv_di">
                <dc:Bounds x="1972.0" y="382.0" width="36.0" height="36.0"/>
            </bpmndi:BPMNShape>
            <bpmndi:BPMNShape bpmnElement="Activity_1orn22c" isExpanded="true" id="Activity_1orn22c_di">
                <dc:Bounds x="270.0" y="-11.0" width="560.0" height="146.0"/>
            </bpmndi:BPMNShape>
            <bpmndi:BPMNShape bpmnElement="Event_0ye7f0f" isExpanded="true" id="Event_0ye7f0f_di">
                <dc:Bounds x="290.0" y="43.0" width="36.0" height="36.0"/>
            </bpmndi:BPMNShape>
            <bpmndi:BPMNShape bpmnElement="Activity_1vnq7vx" isExpanded="true" id="Activity_1vnq7vx_di">
                <dc:Bounds x="380.0" y="21.0" width="100.0" height="80.0"/>
            </bpmndi:BPMNShape>
            <bpmndi:BPMNShape bpmnElement="Event_18geua4" isExpanded="true" id="Event_1caj4vj_di">
                <dc:Bounds x="772.0" y="79.0" width="36.0" height="36.0"/>
            </bpmndi:BPMNShape>
            <bpmndi:BPMNShape bpmnElement="Activity_0hgdfsc" isExpanded="true" id="Activity_08az99f_di">
                <dc:Bounds x="500.0" y="21.0" width="100.0" height="80.0"/>
            </bpmndi:BPMNShape>
            <bpmndi:BPMNShape bpmnElement="Gateway_1uec1ao" isExpanded="true" id="Gateway_1uec1ao_di">
                <dc:Bounds x="645.0" y="36.0" width="50.0" height="50.0"/>
            </bpmndi:BPMNShape>
            <bpmndi:BPMNShape bpmnElement="Event_1c358pb" isExpanded="true" id="BPMNShape_1pgn3e7">
                <dc:Bounds x="772.0" y="9.0" width="36.0" height="36.0"/>
            </bpmndi:BPMNShape>
            <bpmndi:BPMNEdge bpmnElement="Flow_0dmwh1t" id="Flow_0dmwh1t_di">
                <di:waypoint x="326.0" y="61.0"/>
                <di:waypoint x="380.0" y="61.0"/>
            </bpmndi:BPMNEdge>
            <bpmndi:BPMNEdge bpmnElement="Flow_1rgsdw4" id="Flow_1rgsdw4_di">
                <di:waypoint x="480.0" y="61.0"/>
                <di:waypoint x="500.0" y="61.0"/>
            </bpmndi:BPMNEdge>
            <bpmndi:BPMNEdge bpmnElement="Flow_0hubowj" id="Flow_0hubowj_di">
                <di:waypoint x="600.0" y="61.0"/>
                <di:waypoint x="645.0" y="61.0"/>
            </bpmndi:BPMNEdge>
            <bpmndi:BPMNEdge bpmnElement="Flow_0wlz4dd" id="Flow_0wlz4dd_di">
                <di:waypoint x="670.0" y="86.0"/>
                <di:waypoint x="670.0" y="97.0"/>
                <di:waypoint x="772.0" y="97.0"/>
            </bpmndi:BPMNEdge>
            <bpmndi:BPMNEdge bpmnElement="Flow_004vsfw" id="Flow_004vsfw_di">
                <di:waypoint x="670.0" y="36.0"/>
                <di:waypoint x="670.0" y="27.0"/>
                <di:waypoint x="772.0" y="27.0"/>
            </bpmndi:BPMNEdge>
            <bpmndi:BPMNShape bpmnElement="Activity_0u2ji26" isExpanded="true" id="Activity_0u2ji26_di">
                <dc:Bounds x="270.0" y="170.0" width="440.0" height="120.0"/>
            </bpmndi:BPMNShape>
            <bpmndi:BPMNShape bpmnElement="Event_1ycb2rd" isExpanded="true" id="Event_1ycb2rd_di">
                <dc:Bounds x="290.0" y="212.0" width="36.0" height="36.0"/>
            </bpmndi:BPMNShape>
            <bpmndi:BPMNShape bpmnElement="Activity_06yomsp" isExpanded="true" id="Activity_06yomsp_di">
                <dc:Bounds x="380.0" y="190.0" width="100.0" height="80.0"/>
            </bpmndi:BPMNShape>
            <bpmndi:BPMNShape bpmnElement="Event_1lvltfg" isExpanded="true" id="Event_1lrc7td_di">
                <dc:Bounds x="652.0" y="212.0" width="36.0" height="36.0"/>
            </bpmndi:BPMNShape>
            <bpmndi:BPMNShape bpmnElement="Activity_0f2qbi5" isExpanded="true" id="Activity_07d6u33_di">
                <dc:Bounds x="500.0" y="190.0" width="100.0" height="80.0"/>
            </bpmndi:BPMNShape>
            <bpmndi:BPMNEdge bpmnElement="Flow_0rsmpbt" id="Flow_0rsmpbt_di">
                <di:waypoint x="326.0" y="230.0"/>
                <di:waypoint x="380.0" y="230.0"/>
            </bpmndi:BPMNEdge>
            <bpmndi:BPMNEdge bpmnElement="Flow_1e5og53" id="Flow_1e5og53_di">
                <di:waypoint x="480.0" y="230.0"/>
                <di:waypoint x="500.0" y="230.0"/>
            </bpmndi:BPMNEdge>
            <bpmndi:BPMNEdge bpmnElement="Flow_09l4mlz" id="Flow_09l4mlz_di">
                <di:waypoint x="600.0" y="230.0"/>
                <di:waypoint x="652.0" y="230.0"/>
            </bpmndi:BPMNEdge>
            <bpmndi:BPMNShape bpmnElement="Activity_06i9ief" isExpanded="true" id="Activity_06i9ief_di">
                <dc:Bounds x="270.0" y="327.0" width="440.0" height="120.0"/>
            </bpmndi:BPMNShape>
            <bpmndi:BPMNShape bpmnElement="Event_08y1fx0" isExpanded="true" id="Event_08y1fx0_di">
                <dc:Bounds x="290.0" y="369.0" width="36.0" height="36.0"/>
            </bpmndi:BPMNShape>
            <bpmndi:BPMNShape bpmnElement="Event_0nnj983" isExpanded="true" id="Event_00i9wmf_di">
                <dc:Bounds x="652.0" y="369.0" width="36.0" height="36.0"/>
            </bpmndi:BPMNShape>
            <bpmndi:BPMNShape bpmnElement="Activity_1u9j3qq" isExpanded="true" id="Activity_1u9j3qq_di">
                <dc:Bounds x="380.0" y="347.0" width="100.0" height="80.0"/>
            </bpmndi:BPMNShape>
            <bpmndi:BPMNShape bpmnElement="Activity_1vca8j6" isExpanded="true" id="Activity_1qp6z2w_di">
                <dc:Bounds x="500.0" y="347.0" width="100.0" height="80.0"/>
            </bpmndi:BPMNShape>
            <bpmndi:BPMNEdge bpmnElement="Flow_1j4kz66" id="Flow_1j4kz66_di">
                <di:waypoint x="326.0" y="387.0"/>
                <di:waypoint x="380.0" y="387.0"/>
            </bpmndi:BPMNEdge>
            <bpmndi:BPMNEdge bpmnElement="Flow_1361e1h" id="Flow_1361e1h_di">
                <di:waypoint x="480.0" y="387.0"/>
                <di:waypoint x="500.0" y="387.0"/>
            </bpmndi:BPMNEdge>
            <bpmndi:BPMNEdge bpmnElement="Flow_0ftmfkk" id="Flow_0ftmfkk_di">
                <di:waypoint x="600.0" y="387.0"/>
                <di:waypoint x="652.0" y="387.0"/>
            </bpmndi:BPMNEdge>
            <bpmndi:BPMNShape bpmnElement="Activity_1fscgo7" isExpanded="true" id="Activity_1fscgo7_di">
                <dc:Bounds x="900.0" y="0.0" width="428.0" height="124.0"/>
            </bpmndi:BPMNShape>
            <bpmndi:BPMNShape bpmnElement="Event_1p6qwcl" isExpanded="true" id="Event_1p6qwcl_di">
                <dc:Bounds x="920.0" y="46.0" width="36.0" height="36.0"/>
            </bpmndi:BPMNShape>
            <bpmndi:BPMNShape bpmnElement="Event_1xq7ezu" isExpanded="true" id="Event_1hgnz40_di">
                <dc:Bounds x="1272.0" y="46.0" width="36.0" height="36.0"/>
            </bpmndi:BPMNShape>
            <bpmndi:BPMNShape bpmnElement="Activity_1laoi38" isExpanded="true" id="Activity_1laoi38_di">
                <dc:Bounds x="1000.0" y="24.0" width="100.0" height="80.0"/>
            </bpmndi:BPMNShape>
            <bpmndi:BPMNShape bpmnElement="Activity_160zcyt" isExpanded="true" id="Activity_17kshso_di">
                <dc:Bounds x="1120.0" y="24.0" width="100.0" height="80.0"/>
            </bpmndi:BPMNShape>
            <bpmndi:BPMNEdge bpmnElement="Flow_0idb7s1" id="Flow_0idb7s1_di">
                <di:waypoint x="956.0" y="64.0"/>
                <di:waypoint x="1000.0" y="64.0"/>
            </bpmndi:BPMNEdge>
            <bpmndi:BPMNEdge bpmnElement="Flow_1vndndf" id="Flow_1vndndf_di">
                <di:waypoint x="1100.0" y="64.0"/>
                <di:waypoint x="1120.0" y="64.0"/>
            </bpmndi:BPMNEdge>
            <bpmndi:BPMNEdge bpmnElement="Flow_1ebzssr" id="Flow_1ebzssr_di">
                <di:waypoint x="1220.0" y="64.0"/>
                <di:waypoint x="1272.0" y="64.0"/>
            </bpmndi:BPMNEdge>
            <bpmndi:BPMNShape bpmnElement="Activity_1gra44f" isExpanded="true" id="BPMNShape_1mwgyo8">
                <dc:Bounds x="900.0" y="170.0" width="428.0" height="120.0"/>
            </bpmndi:BPMNShape>
            <bpmndi:BPMNShape bpmnElement="Event_1r2kc81" isExpanded="true" id="BPMNShape_0cx29cg">
                <dc:Bounds x="920.0" y="212.0" width="36.0" height="36.0"/>
            </bpmndi:BPMNShape>
            <bpmndi:BPMNShape bpmnElement="Event_05xa35d" isExpanded="true" id="BPMNShape_16fpmq6">
                <dc:Bounds x="1272.0" y="212.0" width="36.0" height="36.0"/>
            </bpmndi:BPMNShape>
            <bpmndi:BPMNShape bpmnElement="Activity_15nyuuv" isExpanded="true" id="Activity_15nyuuv_di">
                <dc:Bounds x="1000.0" y="190.0" width="100.0" height="80.0"/>
            </bpmndi:BPMNShape>
            <bpmndi:BPMNShape bpmnElement="Activity_168xhbo" isExpanded="true" id="Activity_0jkinfo_di">
                <dc:Bounds x="1120.0" y="190.0" width="100.0" height="80.0"/>
            </bpmndi:BPMNShape>
            <bpmndi:BPMNEdge bpmnElement="Flow_036a0dc" id="Flow_036a0dc_di">
                <di:waypoint x="956.0" y="230.0"/>
                <di:waypoint x="1000.0" y="230.0"/>
            </bpmndi:BPMNEdge>
            <bpmndi:BPMNEdge bpmnElement="Flow_0z2dib1" id="Flow_0z2dib1_di">
                <di:waypoint x="1100.0" y="230.0"/>
                <di:waypoint x="1120.0" y="230.0"/>
            </bpmndi:BPMNEdge>
            <bpmndi:BPMNEdge bpmnElement="Flow_05pka45" id="Flow_05pka45_di">
                <di:waypoint x="1220.0" y="230.0"/>
                <di:waypoint x="1272.0" y="230.0"/>
            </bpmndi:BPMNEdge>
            <bpmndi:BPMNShape bpmnElement="Activity_1ctkomf" isExpanded="true" id="BPMNShape_008r01e">
                <dc:Bounds x="900.0" y="330.0" width="428.0" height="120.0"/>
            </bpmndi:BPMNShape>
            <bpmndi:BPMNShape bpmnElement="Event_18ex763" isExpanded="true" id="BPMNShape_1rahbaz">
                <dc:Bounds x="920.0" y="372.0" width="36.0" height="36.0"/>
            </bpmndi:BPMNShape>
            <bpmndi:BPMNShape bpmnElement="Event_048d9vp" isExpanded="true" id="BPMNShape_0nu9b4g">
                <dc:Bounds x="1272.0" y="372.0" width="36.0" height="36.0"/>
            </bpmndi:BPMNShape>
            <bpmndi:BPMNShape bpmnElement="Activity_0lurpn9" isExpanded="true" id="Activity_0lurpn9_di">
                <dc:Bounds x="1000.0" y="350.0" width="100.0" height="80.0"/>
            </bpmndi:BPMNShape>
            <bpmndi:BPMNShape bpmnElement="Activity_0srzvps" isExpanded="true" id="Activity_1ftn6ha_di">
                <dc:Bounds x="1120.0" y="350.0" width="100.0" height="80.0"/>
            </bpmndi:BPMNShape>
            <bpmndi:BPMNEdge bpmnElement="Flow_04qhbvg" id="Flow_04qhbvg_di">
                <di:waypoint x="956.0" y="390.0"/>
                <di:waypoint x="1000.0" y="390.0"/>
            </bpmndi:BPMNEdge>
            <bpmndi:BPMNEdge bpmnElement="Flow_1vroye7" id="Flow_1vroye7_di">
                <di:waypoint x="1100.0" y="390.0"/>
                <di:waypoint x="1120.0" y="390.0"/>
            </bpmndi:BPMNEdge>
            <bpmndi:BPMNEdge bpmnElement="Flow_0v5cyqg" id="Flow_0v5cyqg_di">
                <di:waypoint x="1220.0" y="390.0"/>
                <di:waypoint x="1272.0" y="390.0"/>
            </bpmndi:BPMNEdge>
            <bpmndi:BPMNShape bpmnElement="Activity_1gpw3kp" isExpanded="true" id="BPMNShape_1hmzo3n">
                <dc:Bounds x="1390.0" y="1.0" width="480.0" height="121.0"/>
            </bpmndi:BPMNShape>
            <bpmndi:BPMNShape bpmnElement="Event_109homn" isExpanded="true" id="BPMNShape_0iu5zp8">
                <dc:Bounds x="1410.0" y="44.0" width="36.0" height="36.0"/>
            </bpmndi:BPMNShape>
            <bpmndi:BPMNShape bpmnElement="Event_1fddm07" isExpanded="true" id="BPMNShape_1q5d2tr">
                <dc:Bounds x="1772.0" y="44.0" width="36.0" height="36.0"/>
            </bpmndi:BPMNShape>
            <bpmndi:BPMNShape bpmnElement="Activity_0sy4ge9" isExpanded="true" id="Activity_0sy4ge9_di">
                <dc:Bounds x="1500.0" y="22.0" width="100.0" height="80.0"/>
            </bpmndi:BPMNShape>
            <bpmndi:BPMNShape bpmnElement="Activity_1eti6dl" isExpanded="true" id="Activity_0gkhxzo_di">
                <dc:Bounds x="1620.0" y="22.0" width="100.0" height="80.0"/>
            </bpmndi:BPMNShape>
            <bpmndi:BPMNEdge bpmnElement="Flow_12asyv0" id="Flow_12asyv0_di">
                <di:waypoint x="1446.0" y="62.0"/>
                <di:waypoint x="1500.0" y="62.0"/>
            </bpmndi:BPMNEdge>
            <bpmndi:BPMNEdge bpmnElement="Flow_1c2qcd8" id="Flow_1c2qcd8_di">
                <di:waypoint x="1600.0" y="62.0"/>
                <di:waypoint x="1620.0" y="62.0"/>
            </bpmndi:BPMNEdge>
            <bpmndi:BPMNEdge bpmnElement="Flow_0teseho" id="Flow_0teseho_di">
                <di:waypoint x="1720.0" y="62.0"/>
                <di:waypoint x="1772.0" y="62.0"/>
            </bpmndi:BPMNEdge>
            <bpmndi:BPMNShape bpmnElement="Activity_17pdmja" isExpanded="true" id="BPMNShape_1cu2xxj">
                <dc:Bounds x="1390.0" y="170.0" width="480.0" height="120.0"/>
            </bpmndi:BPMNShape>
            <bpmndi:BPMNShape bpmnElement="Event_0x9jiwi" isExpanded="true" id="BPMNShape_1uvfapx">
                <dc:Bounds x="1410.0" y="212.0" width="36.0" height="36.0"/>
            </bpmndi:BPMNShape>
            <bpmndi:BPMNShape bpmnElement="Event_0xfzeiu" isExpanded="true" id="BPMNShape_0dwu5qs">
                <dc:Bounds x="1772.0" y="212.0" width="36.0" height="36.0"/>
            </bpmndi:BPMNShape>
            <bpmndi:BPMNShape bpmnElement="Activity_0j3imc7" isExpanded="true" id="Activity_0j3imc7_di">
                <dc:Bounds x="1500.0" y="190.0" width="100.0" height="80.0"/>
            </bpmndi:BPMNShape>
            <bpmndi:BPMNShape bpmnElement="Activity_0npdb6z" isExpanded="true" id="Activity_0wog83a_di">
                <dc:Bounds x="1620.0" y="190.0" width="100.0" height="80.0"/>
            </bpmndi:BPMNShape>
            <bpmndi:BPMNEdge bpmnElement="Flow_0fkyri9" id="Flow_0fkyri9_di">
                <di:waypoint x="1446.0" y="230.0"/>
                <di:waypoint x="1500.0" y="230.0"/>
            </bpmndi:BPMNEdge>
            <bpmndi:BPMNEdge bpmnElement="Flow_088i6hx" id="Flow_088i6hx_di">
                <di:waypoint x="1600.0" y="230.0"/>
                <di:waypoint x="1620.0" y="230.0"/>
            </bpmndi:BPMNEdge>
            <bpmndi:BPMNEdge bpmnElement="Flow_1fdo9or" id="Flow_1fdo9or_di">
                <di:waypoint x="1720.0" y="230.0"/>
                <di:waypoint x="1772.0" y="230.0"/>
            </bpmndi:BPMNEdge>
            <bpmndi:BPMNShape bpmnElement="Activity_0xh1h4u" isExpanded="true" id="BPMNShape_1rzra1o">
                <dc:Bounds x="1390.0" y="327.0" width="480.0" height="125.0"/>
            </bpmndi:BPMNShape>
            <bpmndi:BPMNShape bpmnElement="Event_1l4ixtw" isExpanded="true" id="BPMNShape_17jpbjl">
                <dc:Bounds x="1410.0" y="374.0" width="36.0" height="36.0"/>
            </bpmndi:BPMNShape>
            <bpmndi:BPMNShape bpmnElement="Event_0osbixb" isExpanded="true" id="BPMNShape_0ay25tq">
                <dc:Bounds x="1772.0" y="374.0" width="36.0" height="36.0"/>
            </bpmndi:BPMNShape>
            <bpmndi:BPMNShape bpmnElement="Activity_144o4zz" isExpanded="true" id="Activity_144o4zz_di">
                <dc:Bounds x="1500.0" y="352.0" width="100.0" height="80.0"/>
            </bpmndi:BPMNShape>
            <bpmndi:BPMNEdge bpmnElement="Flow_1fxj829" id="Flow_1fxj829_di">
                <di:waypoint x="1446.0" y="392.0"/>
                <di:waypoint x="1500.0" y="392.0"/>
            </bpmndi:BPMNEdge>
            <bpmndi:BPMNEdge bpmnElement="Flow_0g1jr88" id="Flow_0g1jr88_di">
                <di:waypoint x="1600.0" y="392.0"/>
                <di:waypoint x="1772.0" y="392.0"/>
            </bpmndi:BPMNEdge>
            <bpmndi:BPMNShape bpmnElement="Activity_1yfuswa" isExpanded="true" id="Activity_1yfuswa_di">
                <dc:Bounds x="390.0" y="-170.0" width="440.0" height="120.0"/>
            </bpmndi:BPMNShape>
            <bpmndi:BPMNShape bpmnElement="Event_0sgpzpt" isExpanded="true" id="Event_0sgpzpt_di">
                <dc:Bounds x="410.0" y="-128.0" width="36.0" height="36.0"/>
            </bpmndi:BPMNShape>
            <bpmndi:BPMNShape bpmnElement="Activity_075hi0s" isExpanded="true" id="Activity_075hi0s_di">
                <dc:Bounds x="500.0" y="-150.0" width="100.0" height="80.0"/>
            </bpmndi:BPMNShape>
            <bpmndi:BPMNShape bpmnElement="Activity_02fa1v5" isExpanded="true" id="Activity_1a5x4ex_di">
                <dc:Bounds x="620.0" y="-150.0" width="100.0" height="80.0"/>
            </bpmndi:BPMNShape>
            <bpmndi:BPMNShape bpmnElement="Event_1k1zw31" isExpanded="true" id="Event_1nadp30_di">
                <dc:Bounds x="772.0" y="-128.0" width="36.0" height="36.0"/>
            </bpmndi:BPMNShape>
            <bpmndi:BPMNEdge bpmnElement="Flow_1vp2jsr" id="Flow_1vp2jsr_di">
                <di:waypoint x="446.0" y="-110.0"/>
                <di:waypoint x="500.0" y="-110.0"/>
            </bpmndi:BPMNEdge>
            <bpmndi:BPMNEdge bpmnElement="Flow_1xiia3h" id="Flow_1xiia3h_di">
                <di:waypoint x="720.0" y="-110.0"/>
                <di:waypoint x="772.0" y="-110.0"/>
            </bpmndi:BPMNEdge>
            <bpmndi:BPMNEdge bpmnElement="Flow_1dpcxo0" id="Flow_1dpcxo0_di">
                <di:waypoint x="600.0" y="-110.0"/>
                <di:waypoint x="620.0" y="-110.0"/>
            </bpmndi:BPMNEdge>
            <bpmndi:BPMNShape bpmnElement="Gateway_0otd8dt" isExpanded="true" id="Gateway_19jflnv_di">
                <dc:Bounds x="285.0" y="-135.0" width="50.0" height="50.0"/>
            </bpmndi:BPMNShape>
            <bpmndi:BPMNShape bpmnElement="Event_02txiu1" isExpanded="true" id="Event_0ki1k9n_di">
                <dc:Bounds x="372.0" y="-128.0" width="36.0" height="36.0"/>
            </bpmndi:BPMNShape>
            <bpmndi:BPMNShape bpmnElement="Event_19qlw14" isExpanded="true" id="Event_1w16xza_di">
                <dc:Bounds x="602.0" y="-29.0" width="36.0" height="36.0"/>
            </bpmndi:BPMNShape>
            <bpmndi:BPMNShape bpmnElement="Event_011de9s" isExpanded="true" id="Event_1khmhfh_di">
                <dc:Bounds x="1612.0" y="104.0" width="36.0" height="36.0"/>
            </bpmndi:BPMNShape>
            <bpmndi:BPMNShape bpmnElement="Event_1svc0dc" isExpanded="true" id="Event_1sddple_di">
                <dc:Bounds x="1310.0" y="372.0" width="36.0" height="36.0"/>
            </bpmndi:BPMNShape>
            <bpmndi:BPMNShape bpmnElement="Event_0qrvcf0" isExpanded="true" id="Event_0qtguf5_di">
                <dc:Bounds x="1112.0" y="272.0" width="36.0" height="36.0"/>
            </bpmndi:BPMNShape>
            <bpmndi:BPMNShape bpmnElement="Event_0yga7lj" isExpanded="true" id="Event_1g9ztf8_di">
                <dc:Bounds x="1612.0" y="272.0" width="36.0" height="36.0"/>
            </bpmndi:BPMNShape>
            <bpmndi:BPMNShape bpmnElement="Event_1tijolq" isExpanded="true" id="Event_1ycl22d_di">
                <dc:Bounds x="1112.0" y="106.0" width="36.0" height="36.0"/>
            </bpmndi:BPMNShape>
            <bpmndi:BPMNShape bpmnElement="Event_10a8nju" isExpanded="true" id="Event_1ilwyar_di">
                <dc:Bounds x="1852.0" y="382.0" width="36.0" height="36.0"/>
            </bpmndi:BPMNShape>
            <bpmndi:BPMNShape bpmnElement="Event_0s0jisx" isExpanded="true" id="Event_11aopyi_di">
                <dc:Bounds x="692.0" y="369.0" width="36.0" height="36.0"/>
            </bpmndi:BPMNShape>
            <bpmndi:BPMNShape bpmnElement="Event_06mr4j6" isExpanded="true" id="Event_10m0kg7_di">
                <dc:Bounds x="482.0" y="272.0" width="36.0" height="36.0"/>
            </bpmndi:BPMNShape>
            <bpmndi:BPMNShape bpmnElement="Event_00uj5gg" isExpanded="true" id="Event_1xp0nt1_di">
                <dc:Bounds x="482.0" y="117.0" width="36.0" height="36.0"/>
            </bpmndi:BPMNShape>
            <bpmndi:BPMNEdge bpmnElement="Flow_1104ytg" id="Flow_1104ytg_di">
                <di:waypoint x="500.0" y="153.0"/>
                <di:waypoint x="500.0" y="170.0"/>
            </bpmndi:BPMNEdge>
            <bpmndi:BPMNEdge bpmnElement="Flow_02c54hj" id="Flow_02c54hj_di">
                <di:waypoint x="500.0" y="308.0"/>
                <di:waypoint x="500.0" y="327.0"/>
            </bpmndi:BPMNEdge>
            <bpmndi:BPMNEdge bpmnElement="Flow_0a4s7bk" id="Flow_0a4s7bk_di">
                <di:waypoint x="728.0" y="387.0"/>
                <di:waypoint x="860.0" y="387.0"/>
                <di:waypoint x="860.0" y="62.0"/>
                <di:waypoint x="900.0" y="62.0"/>
            </bpmndi:BPMNEdge>
            <bpmndi:BPMNEdge bpmnElement="Flow_1rhkg15" id="Flow_1rhkg15_di">
                <di:waypoint x="1888.0" y="400.0"/>
                <di:waypoint x="1972.0" y="400.0"/>
            </bpmndi:BPMNEdge>
            <bpmndi:BPMNEdge bpmnElement="Flow_01ckbmr" id="Flow_01ckbmr_di">
                <di:waypoint x="1130.0" y="142.0"/>
                <di:waypoint x="1130.0" y="170.0"/>
            </bpmndi:BPMNEdge>
            <bpmndi:BPMNEdge bpmnElement="Flow_0x8q0t7" id="Flow_0x8q0t7_di">
                <di:waypoint x="1130.0" y="308.0"/>
                <di:waypoint x="1130.0" y="330.0"/>
            </bpmndi:BPMNEdge>
            <bpmndi:BPMNEdge bpmnElement="Flow_11bvkd6" id="Flow_11bvkd6_di">
                <di:waypoint x="1346.0" y="390.0"/>
                <di:waypoint x="1360.0" y="390.0"/>
                <di:waypoint x="1360.0" y="62.0"/>
                <di:waypoint x="1390.0" y="62.0"/>
            </bpmndi:BPMNEdge>
            <bpmndi:BPMNEdge bpmnElement="Flow_0s4x984" id="Flow_0s4x984_di">
                <di:waypoint x="1630.0" y="140.0"/>
                <di:waypoint x="1630.0" y="170.0"/>
            </bpmndi:BPMNEdge>
            <bpmndi:BPMNEdge bpmnElement="Flow_0aq2usr" id="Flow_0aq2usr_di">
                <di:waypoint x="1630.0" y="308.0"/>
                <di:waypoint x="1630.0" y="327.0"/>
            </bpmndi:BPMNEdge>
            <bpmndi:BPMNEdge bpmnElement="Flow_18gcg86" id="Flow_18gcg86_di">
                <di:waypoint x="188.0" y="-110.0"/>
                <di:waypoint x="285.0" y="-110.0"/>
            </bpmndi:BPMNEdge>
            <bpmndi:BPMNEdge bpmnElement="Flow_0bgvb9h" id="Flow_0bgvb9h_di">
                <di:waypoint x="620.0" y="-29.0"/>
                <di:waypoint x="620.0" y="-50.0"/>
            </bpmndi:BPMNEdge>
            <bpmndi:BPMNEdge bpmnElement="Flow_1wl760w" id="Flow_1wl760w_di">
                <di:waypoint x="310.0" y="-85.0"/>
                <di:waypoint x="310.0" y="-11.0"/>
            </bpmndi:BPMNEdge>
            <bpmndi:BPMNEdge bpmnElement="Flow_0lbo43z" id="Flow_0lbo43z_di">
                <di:waypoint x="372.0" y="-110.0"/>
                <di:waypoint x="335.0" y="-110.0"/>
            </bpmndi:BPMNEdge>
        </bpmndi:BPMNPlane>
    </bpmndi:BPMNDiagram>
</bpmn:definitions>
